tests/__init__.py
tests/imagetools/__init__.py
tests/imagetools/test_it_misc.py
tests/sourcetools/__init__.py
tests/sourcetools/test_st_misc.py
xga/__init__.py
xga/_version.py
xga/exceptions.py
xga/utils.py
xga/files/add_model_list.txt
xga/files/long_xga_logo.png
xga/files/mission_event_column_name_map.json
xga/files/mult_model_list.txt
xga/files/quick_xga_logo.png
xga/files/sas_errors.csv
xga/files/sas_warnings.csv
xga/files/xspec_model_pars.json5
xga/files/xspec_model_units.json5
xga/imagetools/__init__.py
xga/imagetools/bin.py
xga/imagetools/misc.py
xga/imagetools/profile.py
xga/imagetools/psf.py
xga/imagetools/smooth.py
xga/models/__init__.py
xga/models/base.py
xga/models/density.py
xga/models/entropy.py
xga/models/fitting.py
xga/models/mass.py
xga/models/misc.py
xga/models/pressure.py
xga/models/sb.py
xga/models/temperature.py
xga/products/__init__.py
xga/products/base.py
xga/products/lightcurve.py
xga/products/misc.py
xga/products/phot.py
xga/products/profile.py
xga/products/relation.py
xga/products/spec.py
xga/relations/__init__.py
xga/relations/fit.py
xga/relations/clusters/LT.py
xga/relations/clusters/Lλ.py
xga/relations/clusters/MT.py
xga/relations/clusters/Mλ.py
xga/relations/clusters/RT.py
xga/relations/clusters/TL.py
xga/relations/clusters/Tλ.py
xga/relations/clusters/__init__.py
xga/samples/__init__.py
xga/samples/base.py
xga/samples/extended.py
xga/samples/general.py
xga/samples/point.py
xga/sas/__init__.py
xga/sas/_common.py
xga/sas/lightcurve.py
xga/sas/misc.py
xga/sas/phot.py
xga/sas/run.py
xga/sas/spec.py
xga/sources/__init__.py
xga/sources/base.py
xga/sources/extended.py
xga/sources/general.py
xga/sources/point.py
xga/sourcetools/__init__.py
xga/sourcetools/_common.py
xga/sourcetools/density.py
xga/sourcetools/deproj.py
xga/sourcetools/entropy.py
xga/sourcetools/mass.py
xga/sourcetools/match.py
xga/sourcetools/misc.py
xga/sourcetools/stack.py
xga/sourcetools/temperature.py
xga/tools/__init__.py
xga/tools/clusters/LT.py
xga-0.6.3.dist-info/licenses/LICENSE
xga-0.6.3.dist-info/METADATA
xga-0.6.3.dist-info/WHEEL
xga-0.6.3.dist-info/top_level.txt
xga-0.6.3.dist-info/RECORD
