Metadata-Version: 2.4
Name: xga
Version: 0.6.3
Summary: Python package to easily generate and analyse X-ray astronomy data products, ideal for investigating large samples.
Home-page: http://github.com/DavidT3/XGA
Author: David J Turner
Author-email: djturner@umbc.edu
Requires-Python: >=3.10
License-File: LICENSE
Requires-Dist: astropy>=6.1.2
Requires-Dist: numpy>=1.26.4
Requires-Dist: tqdm>=4.66.4
Requires-Dist: regions>=0.9
Requires-Dist: pandas>=2.2.2
Requires-Dist: fitsio>=1.2.1
Requires-Dist: matplotlib>=3.9.0
Requires-Dist: scipy>=1.14.0
Requires-Dist: pyabel>=0.9
Requires-Dist: corner>=2.2.2
Requires-Dist: emcee>=3.1.6
Requires-Dist: tabulate>=0.9.0
Requires-Dist: getdist>=1.4.7
Requires-Dist: exceptiongroup>=1.0.4
Dynamic: author
Dynamic: author-email
Dynamic: description
Dynamic: description-content-type
Dynamic: home-page
Dynamic: license-file
Dynamic: requires-dist
Dynamic: requires-python
Dynamic: summary
